classic/scenarios/__init__.py
classic/scenarios/exceptions.py
classic/scenarios/scenario.py
classic_scenarios-0.1.0.dist-info/licenses/LICENSE
classic_scenarios-0.1.0.dist-info/METADATA
classic_scenarios-0.1.0.dist-info/WHEEL
classic_scenarios-0.1.0.dist-info/top_level.txt
classic_scenarios-0.1.0.dist-info/RECORD
